acopoweropt/__init__.py
acopoweropt/colony.py
acopoweropt/system.py
acopoweropt-0.3.1.dist-info/LICENSE.md
acopoweropt-0.3.1.dist-info/WHEEL
acopoweropt-0.3.1.dist-info/METADATA
acopoweropt-0.3.1.dist-info/RECORD
