Metadata-Version: 2.1
Name: acopoweropt
Version: 0.3.1
Summary: Ant Colony Power Systems Optimizer
Home-page: https://github.com/ettoreaquino/acopoweropt
Keywords: power systems,optimization,python,ant-colony
Author: Ettore Aquino
Author-email: ettore@ettoreaquino.com
Requires-Python: >=3.8,<4.0
Classifier: Programming Language :: Python :: 3
Classifier: Programming Language :: Python :: 3.8
Classifier: Programming Language :: Python :: 3.9
Requires-Dist: PyQt5 (>=5.15.4,<6.0.0)
Requires-Dist: cvxopt (>=1.2.6,<2.0.0)
Requires-Dist: imageio (>=2.9.0,<3.0.0)
Requires-Dist: matplotlib (>=3.4.2,<4.0.0)
Requires-Dist: pandas (>=1.2.4,<2.0.0)
Requires-Dist: seaborn (>=0.11.1,<0.12.0)
Project-URL: Repository, https://github.com/ettoreaquino/acopoweropt
